fmu_settings_gui/__init__.py
fmu_settings_gui/__main__.py
fmu_settings_gui/_version.py
fmu_settings_gui/py.typed
fmu_settings_gui/static/.gitkeep
fmu_settings_gui/static/favicon.ico
fmu_settings_gui/static/index.html
fmu_settings_gui/static/assets/ProjectSelector-CA7uu16v.js
fmu_settings_gui/static/assets/common-D7_rxYMs.js
fmu_settings_gui/static/assets/ert-cKWLsxhL.png
fmu_settings_gui/static/assets/field-B5157bDc.js
fmu_settings_gui/static/assets/fmu_logo-Cp9Lbuje.png
fmu_settings_gui/static/assets/form-CZz6kKge.js
fmu_settings_gui/static/assets/index-BTWrl1TZ.js
fmu_settings_gui/static/assets/index-CGCOPtAd.js
fmu_settings_gui/static/assets/index-PjrKRrfv.js
fmu_settings_gui/static/assets/keys-BnYr2ZmA.js
fmu_settings_gui/static/assets/masterdata-Dqza6zmL.js
fmu_settings_gui/static/assets/model-kGPbuna_.js
fmu_settings_gui/static/assets/rms-DGgVw3ig.js
fmu_settings_gui/static/assets/sumo-wazaUMRa.png
fmu_settings_gui/static/assets/validator-BVcLZbLS.js
fmu_settings_gui/static/assets/webviz-DzFxZuNs.png
fmu_settings_gui-0.4.0.dist-info/licenses/LICENSE
fmu_settings_gui-0.4.0.dist-info/METADATA
fmu_settings_gui-0.4.0.dist-info/WHEEL
fmu_settings_gui-0.4.0.dist-info/top_level.txt
fmu_settings_gui-0.4.0.dist-info/RECORD
