Metadata-Version: 2.4
Name: fmu-settings-gui
Version: 0.4.0
Summary: The GUI for fmu-settings
Author-email: Equinor <fg-fmu_atlas@equinor.com>
License: GPL-3.0
Project-URL: Homepage, https://github.com/equinor/fmu-settings-gui
Project-URL: Repository, https://github.com/equinor/fmu-settings-gui
Project-URL: Documentation, https://github.com/equinor/fmu-settings-gui
Classifier: Development Status :: 3 - Alpha
Classifier: Topic :: Scientific/Engineering
Classifier: Topic :: Utilities
Classifier: Operating System :: POSIX :: Linux
Classifier: Programming Language :: Python :: 3.11
Classifier: Programming Language :: Python :: 3.12
Classifier: Natural Language :: English
Requires-Python: >=3.11
License-File: LICENSE
Requires-Dist: fastapi
Requires-Dist: uvicorn
Provides-Extra: dev
Requires-Dist: mypy; extra == "dev"
Requires-Dist: pytest; extra == "dev"
Requires-Dist: pytest-cov; extra == "dev"
Requires-Dist: pytest-mock; extra == "dev"
Requires-Dist: pytest-xdist; extra == "dev"
Requires-Dist: ruff; extra == "dev"
Requires-Dist: types-setuptools; extra == "dev"
Dynamic: license-file
